[
  {
    "chunk_id": "e777634e8633_0",
    "url": "https://handbook.gitlab.com/handbook/customer-success/professional-services-engineering/professional-services-delivery-methodology/agile-to-gitlab-terminology",
    "title": "Agile to GitLab Terminology Mapping",
    "source": "handbook",
    "headings": [
      "Agile to GitLab Terminology Mapping"
    ],
    "text": "Agile to GitLab Terminology Mapping\n\nThe following table and blog link show the agile to GitLab terminology mapping.\n\nPoints and estimation\n\nIssue lists and prioritized labels\n\nIssue lists and prioritized labels\n\nBlog: How to use GitLab for Agile Software Development",
    "chunk_index": 0,
    "total_chunks": 1
  }
]